bella/__init__.py
bella/contexts.py
bella/data_types.py
bella/dependency_parsers.py
bella/dependency_tokens.py
bella/error_analysis.py
bella/evaluation.py
bella/helper.py
bella/lexicons.py
bella/moses_tools.py
bella/neural_pooling.py
bella/parsers.py
bella/stanford_tools.py
bella/syntactic_contexts.py
bella/tokenisers.py
bella/word_vectors.py
bella/write_data.py
bella/models/__init__.py
bella/models/base.py
bella/models/target.py
bella/models/tdlstm.py
bella/models/tdparse.py
bella/scikit_features/__init__.py
bella/scikit_features/context.py
bella/scikit_features/debug.py
bella/scikit_features/join_context_vectors.py
bella/scikit_features/lexicon_filter.py
bella/scikit_features/neural_pooling.py
bella/scikit_features/syntactic_context.py
bella/scikit_features/tokeniser.py
bella/scikit_features/word_vector.py
bella_tdsa-0.3.29.dist-info/LICENSE
bella_tdsa-0.3.29.dist-info/METADATA
bella_tdsa-0.3.29.dist-info/WHEEL
bella_tdsa-0.3.29.dist-info/top_level.txt
bella_tdsa-0.3.29.dist-info/RECORD
