Metadata-Version: 2.1
Name: bella-tdsa
Version: 0.3.29
Summary: Target Dependent Sentiment Analysis (TDSA) framework.
Home-page: https://github.com/apmoore1/Bella
Author: Andrew Moore
Author-email: andrew.p.moore94@gmail.com
License: MIT
Platform: UNKNOWN
Classifier: Development Status :: 3 - Alpha
Classifier: License :: OSI Approved :: MIT License
Classifier: Natural Language :: English
Classifier: Programming Language :: Python :: 3.6
Classifier: Topic :: Text Processing
Classifier: Topic :: Text Processing :: Linguistic
Requires-Python: >=3.6.1
Requires-Dist: filelock (>=3.0.10)
Requires-Dist: Keras (>=2.1.3)
Requires-Dist: tensorflow (>=1.3.0)
Requires-Dist: scikit-learn (==0.19.1)
Requires-Dist: gensim (>=3.0.1)
Requires-Dist: requests (>=2.18.4)
Requires-Dist: tqdm (>=4.23.4)
Requires-Dist: twokenize (>=1.0.0)
Requires-Dist: nltk (>=3.2.5)
Requires-Dist: stanfordcorenlp (==3.7.0.2)
Requires-Dist: ftfy (>=5.2.0)
Requires-Dist: ruamel.yaml (>=0.15.34)
Requires-Dist: pandas (>=0.21.0)
Requires-Dist: networkx (>=2.0)
Requires-Dist: tweebo-parser-python-api (>=1.0.4)
Requires-Dist: seaborn (>=0.8.1)
Requires-Dist: spacy (<2.2,>=2.0.18)
Requires-Dist: graphviz (>=0.8.4)
Requires-Dist: pydot (>=1.2.4)
